enable_ai/__init__.py
enable_ai/api_client.py
enable_ai/api_matcher.py
enable_ai/config_loader.py
enable_ai/constants.py
enable_ai/conversation_store.py
enable_ai/environment.py
enable_ai/execution_planner.py
enable_ai/mcp_server.py
enable_ai/orchestrator.py
enable_ai/progress_tracker.py
enable_ai/query_parser.py
enable_ai/response_formatter.py
enable_ai/schema_generator/README.md
enable_ai/schema_generator/__init__.py
enable_ai/schema_generator/base.py
enable_ai/schema_generator/cli.py
enable_ai/schema_generator/schema_converter.py
enable_ai/schema_loader.py
enable_ai/schema_validator.py
enable_ai/types.py
enable_ai/utils.py
enable_ai/workflow.py
enable_ai-0.3.31.dist-info/METADATA
enable_ai-0.3.31.dist-info/WHEEL
enable_ai-0.3.31.dist-info/entry_points.txt
enable_ai-0.3.31.dist-info/licenses/LICENSE
enable_ai-0.3.31.dist-info/RECORD
