Metadata-Version: 2.4
Name: enable-ai
Version: 0.3.31
Summary: AI-powered natural language interface for REST APIs with OpenAPI support and real-time streaming
License: MIT
License-File: LICENSE
Keywords: nlp,api,natural-language,ai,mcp,llm,rest-api,langgraph
Author: Enable Engineering
Requires-Python: >=3.8,<4.0
Classifier: License :: OSI Approved :: MIT License
Classifier: Programming Language :: Python :: 3
Classifier: Programming Language :: Python :: 3.8
Classifier: Programming Language :: Python :: 3.9
Classifier: Programming Language :: Python :: 3.10
Classifier: Programming Language :: Python :: 3.11
Classifier: Programming Language :: Python :: 3.12
Classifier: Programming Language :: Python :: 3.13
Classifier: Programming Language :: Python :: 3.14
Provides-Extra: mcp
Requires-Dist: langgraph (>=0.2.0,<0.3.0)
Requires-Dist: langgraph-checkpoint (>=1.0.0,<2.0.0)
Requires-Dist: openai (>=1.0.0,<2.0.0)
Requires-Dist: python-dotenv (>=0.19.0,<0.20.0)
Requires-Dist: requests (>=2.25.0,<3.0.0)
Project-URL: Homepage, https://github.com/EnableEngineering/enable_ai
Project-URL: Repository, https://github.com/EnableEngineering/enable_ai
